Workbook

Sheet Matrix
A1: ID | B1: Requirement (short) | C1: Full requirement | D1: Module | E1: Objective | F1: Priority | G1: Phase
A2: FR1.1 | B2: Farmer can drop a GPS pin on their land via smartphone to register the plot | C2: Farmer can drop a GPS pin on their land via smartphone to register the plot | D2: Module 1: Feasibility & Offtake | E2: BO1 | F2: Must | G2: 1
A3: FR1.2 | B3: System auto-detects soil type, historical rainfall patterns | C3: System auto-detects soil type, historical rainfall patterns, and acreage from the GPS location, integrating with TIMB's biometric mapping standards | D3: Module 1: Feasibility & Offtake | E3: BO1 | F3: Must | G3: 1
A4: FR1.3 | B4: System auto-generates a 24-month projected cash-flow statement | C4: System auto-generates a 24-month projected cash-flow statement, input requirement schedule, and projected yield model without requiring an extension officer or bank clerk | D4: Module 1: Feasibility & Offtake | E4: BO1 | F4: Must | G4: 1
A5: FR1.4 | B5: Farmer is presented with pre-vetted, standardized offtake contract templates from licensed contractors | C5: Farmer is presented with pre-vetted, standardized offtake contract templates from licensed contractors | D5: Module 1: Feasibility & Offtake | E5: BO2 | F5: Must | G5: 3
A6: FR1.5 | B6: Every contract clause (minimum input packages, grading standards) is translated into plain Shona and Ndebele on screen | C6: Every contract clause (minimum input packages, grading standards) is translated into plain Shona and Ndebele on screen | D6: Module 1: Feasibility & Offtake | E6: BO2 | F6: Must | G6: 3
A7: FR1.6 | B7: System generates a cryptographically secured digital contract upon farmer sign-off | C7: System generates a cryptographically secured digital contract upon farmer sign-off | D7: Module 1: Feasibility & Offtake | E7: BO2 | F7: Must | G7: 3
A8: FR1.7 | B8: System maintains a live credit-scoring ledger from real-time input-utilization tracking | C8: System maintains a live credit-scoring ledger from real-time input-utilization tracking, viewable by financiers to reduce physical verification costs | D8: Module 1: Feasibility & Offtake | E8: BO5 | F8: Must | G8: 3
A9: FR1.8 | B9: What-if tools let the farmer change acreage | C9: What-if tools let the farmer change acreage, input package, expected price, and yield and see the effect on cash flow and break-even before committing | D9: Module 1: Feasibility & Offtake | E9: BO1 | F9: Should | G9: 1
A10: FR1.9 | B10: The feasibility report explains its assumptions in plain language in English | C10: The feasibility report explains its assumptions in plain language in English, Shona, and Ndebele, shows a range rather than a single figure, and states the main risks and the break-even price | D10: Module 1: Feasibility & Offtake | E10: BO1 | F10: Must | G10: 1
A11: FR1.10 | B11: Soil, rainfall, price, and cost benchmarks carry a source and date | C11: Soil, rainfall, price, and cost benchmarks carry a source and date; the farmer can override any figure, and each override is logged | D11: Module 1: Feasibility & Offtake | E11: BO1 | F11: Should | G11: 1
A12: FR1.11 | B12: The report can be printed, exported as PDF | C12: The report can be printed, exported as PDF, or shared with a lender through a consent link, and is stamped with its date and assumption version | D12: Module 1: Feasibility & Offtake | E12: BO5 | F12: Should | G12: 3
... A334: FR5.3 | B334: Human review path and explanation view for any automated credit or compliance decision | C334: Human review path and explanation view for any automated credit or compliance decision | D334: Privacy & Data Protection | E334: All | F334: Should | G334: 2

Sheet Summary
A1: Requirements by module and priority
A3: Module | B3: Must | C3: Should | D3: Could | E3: Total
A4: Module 1: Feasibility & Offtake | B4: =COUNTIFS(Matrix!$D$2:$D$334,$A4,Matrix!$F$2:$F$334,B$3) -> 8 | C4: =COUNTIFS(Matrix!$D$2:$D$334,$A4,Matrix!$F$2:$F$334,C$3) -> 9 | D4: =COUNTIFS(Matrix!$D$2:$D$334,$A4,Matrix!$F$2:$F$334,D$3) -> 0 | E4: =SUM(B4:D4) -> 17
A5: TIMB Gateway & Compliance | B5: =COUNTIFS(Matrix!$D$2:$D$334,$A5,Matrix!$F$2:$F$334,B$3) -> 9 | C5: =COUNTIFS(Matrix!$D$2:$D$334,$A5,Matrix!$F$2:$F$334,C$3) -> 9 | D5: =COUNTIFS(Matrix!$D$2:$D$334,$A5,Matrix!$F$2:$F$334,D$3) -> 0 | E5: =SUM(B5:D5) -> 18
A6: Horticulture Expansion | B6: =COUNTIFS(Matrix!$D$2:$D$334,$A6,Matrix!$F$2:$F$334,B$3) -> 0 | C6: =COUNTIFS(Matrix!$D$2:$D$334,$A6,Matrix!$F$2:$F$334,C$3) -> 8 | D6: =COUNTIFS(Matrix!$D$2:$D$334,$A6,Matrix!$F$2:$F$334,D$3) -> 6 | E6: =SUM(B6:D6) -> 14
A7: Agronomy | B7: =COUNTIFS(Matrix!$D$2:$D$334,$A7,Matrix!$F$2:$F$334,B$3) -> 5 | C7: =COUNTIFS(Matrix!$D$2:$D$334,$A7,Matrix!$F$2:$F$334,C$3) -> 10 | D7: =COUNTIFS(Matrix!$D$2:$D$334,$A7,Matrix!$F$2:$F$334,D$3) -> 1 | E7: =SUM(B7:D7) -> 16
A8: Accounting & Input Escrow | B8: =COUNTIFS(Matrix!$D$2:$D$334,$A8,Matrix!$F$2:$F$334,B$3) -> 14 | C8: =COUNTIFS(Matrix!$D$2:$D$334,$A8,Matrix!$F$2:$F$334,C$3) -> 7 | D8: =COUNTIFS(Matrix!$D$2:$D$334,$A8,Matrix!$F$2:$F$334,D$3) -> 1 | E8: =SUM(B8:D8) -> 22
A9: Marketing & CRM | B9: =COUNTIFS(Matrix!$D$2:$D$334,$A9,Matrix!$F$2:$F$334,B$3) -> 1 | C9: =COUNTIFS(Matrix!$D$2:$D$334,$A9,Matrix!$F$2:$F$334,C$3) -> 3 | D9: =COUNTIFS(Matrix!$D$2:$D$334,$A9,Matrix!$F$2:$F$334,D$3) -> 8 | E9: =SUM(B9:D9) -> 12
A10: Logistics & Transport | B10: =COUNTIFS(Matrix!$D$2:$D$334,$A10,Matrix!$F$2:$F$334,B$3) -> 10 | C10: =COUNTIFS(Matrix!$D$2:$D$334,$A10,Matrix!$F$2:$F$334,C$3) -> 9 | D10: =COUNTIFS(Matrix!$D$2:$D$334,$A10,Matrix!$F$2:$F$334,D$3) -> 4 | E10: =SUM(B10:D10) -> 23
A11: Refrigeration & Storage | B11: =COUNTIFS(Matrix!$D$2:$D$334,$A11,Matrix!$F$2:$F$334,B$3) -> 0 | C11: =COUNTIFS(Matrix!$D$2:$D$334,$A11,Matrix!$F$2:$F$334,C$3) -> 5 | D11: =COUNTIFS(Matrix!$D$2:$D$334,$A11,Matrix!$F$2:$F$334,D$3) -> 9 | E11: =SUM(B11:D11) -> 14
A12: Ecommerce Marketplace | B12: =COUNTIFS(Matrix!$D$2:$D$334,$A12,Matrix!$F$2:$F$334,B$3) -> 1 | C12: =COUNTIFS(Matrix!$D$2:$D$334,$A12,Matrix!$F$2:$F$334,C$3) -> 7 | D12: =COUNTIFS(Matrix!$D$2:$D$334,$A12,Matrix!$F$2:$F$334,D$3) -> 8 | E12: =SUM(B12:D12) -> 16
A13: Consumer, Retailer & Offtaker | B13: =COUNTIFS(Matrix!$D$2:$D$334,$A13,Matrix!$F$2:$F$334,B$3) -> 6 | C13: =COUNTIFS(Matrix!$D$2:$D$334,$A13,Matrix!$F$2:$F$334,C$3) -> 10 | D13: =COUNTIFS(Matrix!$D$2:$D$334,$A13,Matrix!$F$2:$F$334,D$3) -> 6 | E13: =SUM(B13:D13) -> 22
A14: Auction Floors & Exchange | B14: =COUNTIFS(Matrix!$D$2:$D$334,$A14,Matrix!$F$2:$F$334,B$3) -> 7 | C14: =COUNTIFS(Matrix!$D$2:$D$334,$A14,Matrix!$F$2:$F$334,C$3) -> 6 | D14: =COUNTIFS(Matrix!$D$2:$D$334,$A14,Matrix!$F$2:$F$334,D$3) -> 6 | E14: =SUM(B14:D14) -> 19
A15: Advisor Desk | B15: =COUNTIFS(Matrix!$D$2:$D$334,$A15,Matrix!$F$2:$F$334,B$3) -> 0 | C15: =COUNTIFS(Matrix!$D$2:$D$334,$A15,Matrix!$F$2:$F$334,C$3) -> 9 | D15: =COUNTIFS(Matrix!$D$2:$D$334,$A15,Matrix!$F$2:$F$334,D$3) -> 4 | E15: =SUM(B15:D15) -> 13
... A25: Privacy & Data Protection | B25: =COUNTIFS(Matrix!$D$2:$D$334,$A25,Matrix!$F$2:$F$334,B$3) -> 1 | C25: =COUNTIFS(Matrix!$D$2:$D$334,$A25,Matrix!$F$2:$F$334,C$3) -> 2 | D25: =COUNTIFS(Matrix!$D$2:$D$334,$A25,Matrix!$F$2:$F$334,D$3) -> 0 | E25: =SUM(B25:D25) -> 3
A26: Total | B26: =SUM(B4:B25) -> 128 | C26: =SUM(C4:C25) -> 135 | D26: =SUM(D4:D25) -> 70 | E26: =SUM(E4:E25) -> 333
A28: Requirements by phase and priority
A29: Phase | B29: Must | C29: Should | D29: Could | E29: Total
A30: 1 | B30: =COUNTIFS(Matrix!$G$2:$G$334,$A30,Matrix!$F$2:$F$334,B$29) -> 69 | C30: =COUNTIFS(Matrix!$G$2:$G$334,$A30,Matrix!$F$2:$F$334,C$29) -> 28 | D30: =COUNTIFS(Matrix!$G$2:$G$334,$A30,Matrix!$F$2:$F$334,D$29) -> 0 | E30: =SUM(B30:D30) -> 97
A31: 2 | B31: =COUNTIFS(Matrix!$G$2:$G$334,$A31,Matrix!$F$2:$F$334,B$29) -> 15 | C31: =COUNTIFS(Matrix!$G$2:$G$334,$A31,Matrix!$F$2:$F$334,C$29) -> 21 | D31: =COUNTIFS(Matrix!$G$2:$G$334,$A31,Matrix!$F$2:$F$334,D$29) -> 1 | E31: =SUM(B31:D31) -> 37
A32: 3 | B32: =COUNTIFS(Matrix!$G$2:$G$334,$A32,Matrix!$F$2:$F$334,B$29) -> 28 | C32: =COUNTIFS(Matrix!$G$2:$G$334,$A32,Matrix!$F$2:$F$334,C$29) -> 48 | D32: =COUNTIFS(Matrix!$G$2:$G$334,$A32,Matrix!$F$2:$F$334,D$29) -> 0 | E32: =SUM(B32:D32) -> 76
A33: 4 | B33: =COUNTIFS(Matrix!$G$2:$G$334,$A33,Matrix!$F$2:$F$334,B$29) -> 16 | C33: =COUNTIFS(Matrix!$G$2:$G$334,$A33,Matrix!$F$2:$F$334,C$29) -> 36 | D33: =COUNTIFS(Matrix!$G$2:$G$334,$A33,Matrix!$F$2:$F$334,D$29) -> 0 | E33: =SUM(B33:D33) -> 52
A34: Post-pilot | B34: =COUNTIFS(Matrix!$G$2:$G$334,$A34,Matrix!$F$2:$F$334,B$29) -> 0 | C34: =COUNTIFS(Matrix!$G$2:$G$334,$A34,Matrix!$F$2:$F$334,C$29) -> 2 | D34: =COUNTIFS(Matrix!$G$2:$G$334,$A34,Matrix!$F$2:$F$334,D$29) -> 69 | E34: =SUM(B34:D34) -> 71

Sheet Legend
A1: Item | B1: Meaning
A2: Priority | B2: Must = needed for the pilot or for legal and statutory compliance; Should = important but not blocking; Could = later or optional
A3: Phase | B3: 1 standalone farmer tools; 2 regulatory and compliance gateways; 3 logistics and escrow; 4 offtakers and retailers; Post-pilot = after the Cluster-Zero pilot
A4: BO1 | B4: Make Transfarmation indispensable to the individual communal farmer without network effects
A5: BO2 | B5: Replace opaque paper contract farming with a transparent, financeable digital process
A6: BO3 | B6: Reduce side-marketing losses through biometric grower and GPS verification
A7: BO4 | B7: Automate statutory levy collection and environmental compliance at point of sale
A8: BO5 | B8: De-risk input financing for banks and merchants with real-time credit-scoring data
A9: BO6 | B9: Prove a reusable module architecture that extends to horticulture and other verticals
A10: All | B10: Cross-cutting requirement that supports every objective
A11: Note | B11: Priority and phase are proposals made when drafting the BRD, based on the roadmap and feature prioritization; review them with the team before build. Edit the Matrix sheet and the Summary sheet updates by formula.
